{
  "db_name": "PostgreSQL",
  "query": "\n            select *\n            from lists\n            where (lists.title ilike '%' || $1 || '%')\n            and lists.ap_user_id = $2\n            limit 10\n        ",
  "describe": {
    "columns": [
      {
        "ordinal": 0,
        "name": "id",
        "type_info": "Uuid"
      },
      {
        "ordinal": 1,
        "name": "created_at",
        "type_info": "Timestamptz"
      },
      {
        "ordinal": 2,
        "name": "title",
        "type_info": "Text"
      },
      {
        "ordinal": 3,
        "name": "content",
        "type_info": "Text"
      },
      {
        "ordinal": 4,
        "name": "private",
        "type_info": "Bool"
      },
      {
        "ordinal": 5,
        "name": "pinned",
        "type_info": "Bool"
      },
      {
        "ordinal": 6,
        "name": "ap_user_id",
        "type_info": "Uuid"
      }
    ],
    "parameters": {
      "Left": [
        "Text",
        "Uuid"
      ]
    },
    "nullable": [
      false,
      false,
      false,
      true,
      false,
      false,
      false
    ]
  },
  "hash": "5f2ccb6aed8ce4f257b6f9645b01f64d8313bd8d60eaf70e20f0c2736d3f6181"
}
